{
  "album_type": "album", 
  "release_date_precision": "year", 
  "external_urls": {
    "spotify": "https://open.spotify.com/album/3mvdHEE56sgj1NtTnTF8qK"
  }, 
  "release_date": "1971", 
  "popularity": 39, 
  "genres": [], 
  "uri": "spotify:album:3mvdHEE56sgj1NtTnTF8qK", 
  "tracks": {
    "items": [
      {
        "name": "Miss Judy's Farm", 
        "external_urls": {
          "spotify": "https://open.spotify.com/track/4hHhgB1HaNlQG4Y7XNOwhM"
        }, 
        "explicit": false, 
        "preview_url": "https://p.scdn.co/mp3-preview/897f83f1317bbfe4336bea7d4c31adb2220e0ffa", 
        "is_playable": true, 
        "uri": "spotify:track:4hHhgB1HaNlQG4Y7XNOwhM", 
        "disc_number": 1, 
        "href": "https://api.spotify.com/v1/tracks/4hHhgB1HaNlQG4Y7XNOwhM", 
        "artists": [
          {
            "name": "Faces", 
            "external_urls": {
              "spotify": "https://open.spotify.com/artist/3v4feUQnU3VEUqFrjmtekL"
            }, 
            "uri": "spotify:artist:3v4feUQnU3VEUqFrjmtekL", 
            "href": "https://api.spotify.com/v1/artists/3v4feUQnU3VEUqFrjmtekL", 
            "type": "artist", 
            "id": "3v4feUQnU3VEUqFrjmtekL"
          }
        ], 
        "duration_ms": 219533, 
        "track_number": 1, 
        "type": "track", 
        "id": "4hHhgB1HaNlQG4Y7XNOwhM"
      }, 
      {
        "name": "You're So Rude", 
        "external_urls": {
          "spotify": "https://open.spotify.com/track/5tk9bhdIC64SURaS9he35m"
        }, 
        "explicit": false, 
        "preview_url": "https://p.scdn.co/mp3-preview/e4ee10523c85df77d11c4e630b68536e68b12f89", 
        "is_playable": true, 
        "uri": "spotify:track:5tk9bhdIC64SURaS9he35m", 
        "disc_number": 1, 
        "href": "https://api.spotify.com/v1/tracks/5tk9bhdIC64SURaS9he35m", 
        "artists": [
          {
            "name": "Faces", 
            "external_urls": {
              "spotify": "https://open.spotify.com/artist/3v4feUQnU3VEUqFrjmtekL"
            }, 
            "uri": "spotify:artist:3v4feUQnU3VEUqFrjmtekL", 
            "href": "https://api.spotify.com/v1/artists/3v4feUQnU3VEUqFrjmtekL", 
            "type": "artist", 
            "id": "3v4feUQnU3VEUqFrjmtekL"
          }
        ], 
        "duration_ms": 223240, 
        "track_number": 2, 
        "type": "track", 
        "id": "5tk9bhdIC64SURaS9he35m"
      }, 
      {
        "name": "Love Lives Here", 
        "external_urls": {
          "spotify": "https://open.spotify.com/track/2xHnizYdZ4xddyHzC5vs4B"
        }, 
        "explicit": false, 
        "preview_url": "https://p.scdn.co/mp3-preview/64e59789d778a30b23f4fb57d62ebdb32ac5cd75", 
        "is_playable": true, 
        "uri": "spotify:track:2xHnizYdZ4xddyHzC5vs4B", 
        "disc_number": 1, 
        "href": "https://api.spotify.com/v1/tracks/2xHnizYdZ4xddyHzC5vs4B", 
        "artists": [
          {
            "name": "Faces", 
            "external_urls": {
              "spotify": "https://open.spotify.com/artist/3v4feUQnU3VEUqFrjmtekL"
            }, 
            "uri": "spotify:artist:3v4feUQnU3VEUqFrjmtekL", 
            "href": "https://api.spotify.com/v1/artists/3v4feUQnU3VEUqFrjmtekL", 
            "type": "artist", 
            "id": "3v4feUQnU3VEUqFrjmtekL"
          }
        ], 
        "duration_ms": 186333, 
        "track_number": 3, 
        "type": "track", 
        "id": "2xHnizYdZ4xddyHzC5vs4B"
      }, 
      {
        "name": "Last Orders Please", 
        "external_urls": {
          "spotify": "https://open.spotify.com/track/49iErK8RFne4UwwlF2DhwF"
        }, 
        "explicit": false, 
        "preview_url": "https://p.scdn.co/mp3-preview/378413a5e9dceb5f8113ae7535ece3cbd753333f", 
        "is_playable": true, 
        "uri": "spotify:track:49iErK8RFne4UwwlF2DhwF", 
        "disc_number": 1, 
        "href": "https://api.spotify.com/v1/tracks/49iErK8RFne4UwwlF2DhwF", 
        "artists": [
          {
            "name": "Faces", 
            "external_urls": {
              "spotify": "https://open.spotify.com/artist/3v4feUQnU3VEUqFrjmtekL"
            }, 
            "uri": "spotify:artist:3v4feUQnU3VEUqFrjmtekL", 
            "href": "https://api.spotify.com/v1/artists/3v4feUQnU3VEUqFrjmtekL", 
            "type": "artist", 
            "id": "3v4feUQnU3VEUqFrjmtekL"
          }
        ], 
        "duration_ms": 155226, 
        "track_number": 4, 
        "type": "track", 
        "id": "49iErK8RFne4UwwlF2DhwF"
      }, 
      {
        "linked_from": {
          "external_urls": {
            "spotify": "https://open.spotify.com/track/7fLTytvnvxy653VWxflTRf"
          }, 
          "href": "https://api.spotify.com/v1/tracks/7fLTytvnvxy653VWxflTRf", 
          "type": "track", 
          "id": "7fLTytvnvxy653VWxflTRf", 
          "uri": "spotify:track:7fLTytvnvxy653VWxflTRf"
        }, 
        "name": "Stay With Me (Remastered Album Version)", 
        "external_urls": {
          "spotify": "https://open.spotify.com/track/01zQWJiV8VAiHRwedzWK1w"
        }, 
        "explicit": false, 
        "preview_url": "https://p.scdn.co/mp3-preview/55e28767a2ce43e4fd68754c087aca63e971c13d", 
        "is_playable": true, 
        "uri": "spotify:track:01zQWJiV8VAiHRwedzWK1w", 
        "disc_number": 1, 
        "href": "https://api.spotify.com/v1/tracks/01zQWJiV8VAiHRwedzWK1w", 
        "artists": [
          {
            "name": "Faces", 
            "external_urls": {
              "spotify": "https://open.spotify.com/artist/3v4feUQnU3VEUqFrjmtekL"
            }, 
            "uri": "spotify:artist:3v4feUQnU3VEUqFrjmtekL", 
            "href": "https://api.spotify.com/v1/artists/3v4feUQnU3VEUqFrjmtekL", 
            "type": "artist", 
            "id": "3v4feUQnU3VEUqFrjmtekL"
          }
        ], 
        "duration_ms": 279840, 
        "track_number": 12, 
        "type": "track", 
        "id": "01zQWJiV8VAiHRwedzWK1w"
      }, 
      {
        "name": "Debris", 
        "external_urls": {
          "spotify": "https://open.spotify.com/track/2gFXQQ7dDY4lquHpUNeDTM"
        }, 
        "explicit": false, 
        "preview_url": "https://p.scdn.co/mp3-preview/e452ca38f91c74af3aa866bf9624d370e64f1cec", 
        "is_playable": true, 
        "uri": "spotify:track:2gFXQQ7dDY4lquHpUNeDTM", 
        "disc_number": 1, 
        "href": "https://api.spotify.com/v1/tracks/2gFXQQ7dDY4lquHpUNeDTM", 
        "artists": [
          {
            "name": "Faces", 
            "external_urls": {
              "spotify": "https://open.spotify.com/artist/3v4feUQnU3VEUqFrjmtekL"
            }, 
            "uri": "spotify:artist:3v4feUQnU3VEUqFrjmtekL", 
            "href": "https://api.spotify.com/v1/artists/3v4feUQnU3VEUqFrjmtekL", 
            "type": "artist", 
            "id": "3v4feUQnU3VEUqFrjmtekL"
          }
        ], 
        "duration_ms": 276600, 
        "track_number": 6, 
        "type": "track", 
        "id": "2gFXQQ7dDY4lquHpUNeDTM"
      }, 
      {
        "name": "Memphis, Tennessee", 
        "external_urls": {
          "spotify": "https://open.spotify.com/track/3Z0OG6hKVfKqLpFtacUUDe"
        }, 
        "explicit": false, 
        "preview_url": "https://p.scdn.co/mp3-preview/7c1bc9da6c26de5de77676bb7198823d12f263df", 
        "is_playable": true, 
        "uri": "spotify:track:3Z0OG6hKVfKqLpFtacUUDe", 
        "disc_number": 1, 
        "href": "https://api.spotify.com/v1/tracks/3Z0OG6hKVfKqLpFtacUUDe", 
        "artists": [
          {
            "name": "Faces", 
            "external_urls": {
              "spotify": "https://open.spotify.com/artist/3v4feUQnU3VEUqFrjmtekL"
            }, 
            "uri": "spotify:artist:3v4feUQnU3VEUqFrjmtekL", 
            "href": "https://api.spotify.com/v1/artists/3v4feUQnU3VEUqFrjmtekL", 
            "type": "artist", 
            "id": "3v4feUQnU3VEUqFrjmtekL"
          }
        ], 
        "duration_ms": 327760, 
        "track_number": 7, 
        "type": "track", 
        "id": "3Z0OG6hKVfKqLpFtacUUDe"
      }, 
      {
        "name": "Too Bad", 
        "external_urls": {
          "spotify": "https://open.spotify.com/track/65cjfB9WUuumYPHIDPaAsZ"
        }, 
        "explicit": false, 
        "preview_url": "https://p.scdn.co/mp3-preview/bb4aa59cb6e4a9b14e3fe4106c7c4fb29747ae65", 
        "is_playable": true, 
        "uri": "spotify:track:65cjfB9WUuumYPHIDPaAsZ", 
        "disc_number": 1, 
        "href": "https://api.spotify.com/v1/tracks/65cjfB9WUuumYPHIDPaAsZ", 
        "artists": [
          {
            "name": "Faces", 
            "external_urls": {
              "spotify": "https://open.spotify.com/artist/3v4feUQnU3VEUqFrjmtekL"
            }, 
            "uri": "spotify:artist:3v4feUQnU3VEUqFrjmtekL", 
            "href": "https://api.spotify.com/v1/artists/3v4feUQnU3VEUqFrjmtekL", 
            "type": "artist", 
            "id": "3v4feUQnU3VEUqFrjmtekL"
          }
        ], 
        "duration_ms": 193506, 
        "track_number": 8, 
        "type": "track", 
        "id": "65cjfB9WUuumYPHIDPaAsZ"
      }, 
      {
        "linked_from": {
          "external_urls": {
            "spotify": "https://open.spotify.com/track/12MabTVkxPIBCjAqWbuKoJ"
          }, 
          "href": "https://api.spotify.com/v1/tracks/12MabTVkxPIBCjAqWbuKoJ", 
          "type": "track", 
          "id": "12MabTVkxPIBCjAqWbuKoJ", 
          "uri": "spotify:track:12MabTVkxPIBCjAqWbuKoJ"
        }, 
        "name": "That's All You Need - Remastered", 
        "external_urls": {
          "spotify": "https://open.spotify.com/track/5n1dPdW7sksL7rCTlAxF2F"
        }, 
        "explicit": false, 
        "preview_url": "https://p.scdn.co/mp3-preview/dfc615c3d62d9735a4ef07729c70fa3a73977814", 
        "is_playable": true, 
        "uri": "spotify:track:5n1dPdW7sksL7rCTlAxF2F", 
        "disc_number": 1, 
        "href": "https://api.spotify.com/v1/tracks/5n1dPdW7sksL7rCTlAxF2F", 
        "artists": [
          {
            "name": "Faces", 
            "external_urls": {
              "spotify": "https://open.spotify.com/artist/3v4feUQnU3VEUqFrjmtekL"
            }, 
            "uri": "spotify:artist:3v4feUQnU3VEUqFrjmtekL", 
            "href": "https://api.spotify.com/v1/artists/3v4feUQnU3VEUqFrjmtekL", 
            "type": "artist", 
            "id": "3v4feUQnU3VEUqFrjmtekL"
          }
        ], 
        "duration_ms": 306066, 
        "track_number": 6, 
        "type": "track", 
        "id": "5n1dPdW7sksL7rCTlAxF2F"
      }
    ], 
    "next": null, 
    "href": "https://api.spotify.com/v1/albums/3mvdHEE56sgj1NtTnTF8qK/tracks?offset=0&limit=50&market=GB", 
    "limit": 50, 
    "offset": 0, 
    "total": 9, 
    "previous": null
  }, 
  "href": "https://api.spotify.com/v1/albums/3mvdHEE56sgj1NtTnTF8qK", 
  "copyrights": [
    {
      "text": "1971 Warner Brothers Records", 
      "type": "C"
    }, 
    {
      "text": "1971 Warner Brothers Records", 
      "type": "P"
    }
  ], 
  "artists": [
    {
      "name": "Faces", 
      "external_urls": {
        "spotify": "https://open.spotify.com/artist/3v4feUQnU3VEUqFrjmtekL"
      }, 
      "uri": "spotify:artist:3v4feUQnU3VEUqFrjmtekL", 
      "href": "https://api.spotify.com/v1/artists/3v4feUQnU3VEUqFrjmtekL", 
      "type": "artist", 
      "id": "3v4feUQnU3VEUqFrjmtekL"
    }
  ], 
  "images": [
    {
      "url": "https://i.scdn.co/image/33e6a3a3fb3d93ca2d94b6268b39b65e38484868", 
      "width": 640, 
      "height": 640
    }, 
    {
      "url": "https://i.scdn.co/image/6ec2f01c5460588012e84263a2cbba0ad783e49e", 
      "width": 300, 
      "height": 300
    }, 
    {
      "url": "https://i.scdn.co/image/3c41a30dc0de0ece9f344bc581373bbcab64b1f3", 
      "width": 64, 
      "height": 64
    }
  ], 
  "external_ids": {
    "upc": "075992592963"
  }, 
  "type": "album", 
  "id": "3mvdHEE56sgj1NtTnTF8qK", 
  "name": "A Nod Is As Good As A Wink To A Blind Horse"
}